{
  "metadata": {
    "generated_at": "2026-02-04T05:56:33.766Z",
    "ledger_index": 6060472,
    "reward_addresses": [
      "rGBKxoTcavpfEso7ASRELZAMcCMqKa8oFk",
      "rKt4peDozpRW9zdYGiTZC54DSNU3Af6pQE",
      "rJNwqDPKSkbqDPNoNxbW6C3KCS84ZaQc96",
      "rKddMw1hqMGwfgJvzjbWQHtBQT8hDcZNCP",
      "rs3YdBLJHFGhcPKtbMwQgkbrpo1YjyajTP",
      "rscWPz4aA4GtQKH5tYvVFwteiSSjTjounC",
      "rJNBxuus1TjCq3pikYUsKUXXwyBsJqQAt9",
      "rD9LaW5h5AeGoHsPARWNegfZs3XpeNrv9w",
      "rBDbRYd8H7gB6mdNTRssgNvsw8Z6c4riDb",
      "rhczhWeG3eSohzcH5jw8m8Ynca9cgH4eZm",
      "rPThdoLYRDNkcook9MxGP4WV7tiN5xnsTJ",
      "rEpmxYQXvAffdiBu21ewXXZcqzmhapn2Dm"
    ],
    "memo_address": "rwdm72S9YVKkZjeADKU2bbUMuY4vPnSfH7",
    "reward_txs_fetched": 502,
    "memo_txs_fetched": 1075
  },
  "network_totals": {
    "total_pft_distributed": 1705826.02,
    "unique_earners": 27,
    "total_rewards_paid": 289,
    "total_submissions": 744,
    "unique_submitters": 39
  },
  "rewards": {
    "total_pft_distributed": 1705826.02,
    "unique_recipients": 27,
    "total_reward_transactions": 289,
    "leaderboard": [
      {
        "address": "rDqf4nowC2PAZgn1UGHDn46mcUMREYJrsr",
        "total_pft": 565798.75,
        "balance": 564809.75
      },
      {
        "address": "rh7eykJ99XnGTm2iNBzeD5A9MLqnb7kXCp",
        "total_pft": 235795.27,
        "balance": 224586.4
      },
      {
        "address": "rPo8GkCA9YMKzuJGTHbj11kdVfPqSJHxNx",
        "total_pft": 182125,
        "balance": 176802
      },
      {
        "address": "rnmLkDT2SBeaFA5z2ogdUCbJ2GMzn2sLLu",
        "total_pft": 174675,
        "balance": 174676
      },
      {
        "address": "rH3dfGifdXzghxKXS74WRA3WtdKLKGj5Um",
        "total_pft": 86300,
        "balance": 86311
      },
      {
        "address": "r4LPPHygwNnM5d9xtFDnR9hsBqyQQKauGh",
        "total_pft": 65350,
        "balance": 65311
      },
      {
        "address": "rHTgM9rZBZkuqF5H8DQxFWTR7biXmMvPLm",
        "total_pft": 53875,
        "balance": 53896
      },
      {
        "address": "rDxG2EXUmQThZJtZcq4cp18obb8gU7oxuR",
        "total_pft": 52500,
        "balance": 52500
      },
      {
        "address": "rQhV9rE7cs5zgFZohjVjjbwqcMkwpLb9rE",
        "total_pft": 43750,
        "balance": 43761
      },
      {
        "address": "r9oHNN143VkaVeQ5kfQnRyc9gwL8HhSa32",
        "total_pft": 38500,
        "balance": 38511
      },
      {
        "address": "rDAokUXBoYRRqwB3z97t7EsS4ASdXopfo1",
        "total_pft": 28000,
        "balance": 35788.77
      },
      {
        "address": "rpc9FcxtaNVdWonAXv3rABecNLx7kcA3sY",
        "total_pft": 32500,
        "balance": 32511
      },
      {
        "address": "rpyTMcAKiCxqY7VXenD5ercGGzGWNV9xpg",
        "total_pft": 22809.5,
        "balance": 22820.5
      },
      {
        "address": "rafVsZMGoPbMfaJi3Ty8fTWVA2cfq8an5C",
        "total_pft": 14125,
        "balance": 14131
      },
      {
        "address": "rHTicnqEJ7YnPLCHmBtQCjWzXZZ48zAaLV",
        "total_pft": 14000,
        "balance": 14011.2
      },
      {
        "address": "rfo5PXejjp6xA4H8cNhodhkfz9tHLMCVNx",
        "total_pft": 14000,
        "balance": 14011
      },
      {
        "address": "rGGodJFqgreLgXKVGspkZ68dqBH8RBGCJr",
        "total_pft": 13972.5,
        "balance": 13983.5
      },
      {
        "address": "r4r2Kfe7hH72gb1owkkrWa9miHE9n3xJi4",
        "total_pft": 11750,
        "balance": 11761
      },
      {
        "address": "r4WS8fhYgpvnV5j4qkb7yvbt96Bvx9gMZH",
        "total_pft": 10000,
        "balance": 10011
      },
      {
        "address": "rKZ9SVg1z764ABrLQ3Q1Dh5PPR7gM1z4Df",
        "total_pft": 7500,
        "balance": 7511
      },
      {
        "address": "rsAGhYorBXGmbDGXR23iwnENSwSuoMfkQZ",
        "total_pft": 4000,
        "balance": 7343.4
      },
      {
        "address": "rMghCB7NxDV3PfgFTLkzF1YT2KovKEFRWN",
        "total_pft": 6750,
        "balance": 6761
      },
      {
        "address": "rpsfr7P9R9euCE7uThnusiYaWe9QWYnhcZ",
        "total_pft": 6000,
        "balance": 6110
      },
      {
        "address": "rHC35vMWnhC778Zie16XiLzpeUKeQrxQ8b",
        "total_pft": 6000,
        "balance": 6106
      },
      {
        "address": "rGu432jQ34PcCUZyDkujpQPByVCA4LDcw9",
        "total_pft": 6000,
        "balance": 6011
      }
    ],
    "daily_activity": [
      {
        "date": "2026-01-21",
        "pft": 44450,
        "tx_count": 9
      },
      {
        "date": "2026-01-22",
        "pft": 34275,
        "tx_count": 21
      },
      {
        "date": "2026-01-23",
        "pft": 19750,
        "tx_count": 11
      },
      {
        "date": "2026-01-24",
        "pft": 46000,
        "tx_count": 8
      },
      {
        "date": "2026-01-25",
        "pft": 10500,
        "tx_count": 3
      },
      {
        "date": "2026-01-26",
        "pft": 4500,
        "tx_count": 1
      },
      {
        "date": "2026-01-27",
        "pft": 6750,
        "tx_count": 2
      },
      {
        "date": "2026-01-28",
        "pft": 20000,
        "tx_count": 4
      },
      {
        "date": "2026-01-29",
        "pft": 22375,
        "tx_count": 4
      },
      {
        "date": "2026-01-30",
        "pft": 263401.25,
        "tx_count": 46
      },
      {
        "date": "2026-01-31",
        "pft": 102510,
        "tx_count": 16
      },
      {
        "date": "2026-02-01",
        "pft": 203325,
        "tx_count": 32
      },
      {
        "date": "2026-02-02",
        "pft": 553390.63,
        "tx_count": 74
      },
      {
        "date": "2026-02-03",
        "pft": 245540.63,
        "tx_count": 38
      },
      {
        "date": "2026-02-04",
        "pft": 129058.52,
        "tx_count": 20
      }
    ],
    "recent_rewards": [
      {
        "hash": "1B18E389060165331E7638C1A3E1FED029837945620BE409A72A805D5E1751ED",
        "recipient": "rH3dfGifdXzghxKXS74WRA3WtdKLKGj5Um",
        "pft": 9500,
        "timestamp": 1770180321,
        "date": "2026-02-04"
      },
      {
        "hash": "795A9F55539017061F8A5768FD506CD1EFCCB2C64C47A6D6E788D112A14CBF67",
        "recipient": "rnmLkDT2SBeaFA5z2ogdUCbJ2GMzn2sLLu",
        "pft": 6250,
        "timestamp": 1770173941,
        "date": "2026-02-04"
      },
      {
        "hash": "8A545690871C74F9843098CAB2BAB2748A78DFA3312DAD8B5241E174A384863B",
        "recipient": "rHTgM9rZBZkuqF5H8DQxFWTR7biXmMvPLm",
        "pft": 7200,
        "timestamp": 1770172293,
        "date": "2026-02-04"
      },
      {
        "hash": "8A6162977B14FD502F9B019117B3590652B7776054917C07CFC12D9FFA2A7C00",
        "recipient": "rpyTMcAKiCxqY7VXenD5ercGGzGWNV9xpg",
        "pft": 4500,
        "timestamp": 1770168230,
        "date": "2026-02-04"
      },
      {
        "hash": "1D9E70EADFDF4912EE30FC6F157B543A4B2D80DE754FF9262F6DB522DB07E465",
        "recipient": "rnmLkDT2SBeaFA5z2ogdUCbJ2GMzn2sLLu",
        "pft": 6250,
        "timestamp": 1770166011,
        "date": "2026-02-04"
      },
      {
        "hash": "05CFBB1E91163EECF30BD3C2FA65B9ADA97999E0A8192D246E5E6D35D22BAE02",
        "recipient": "rDqf4nowC2PAZgn1UGHDn46mcUMREYJrsr",
        "pft": 9800,
        "timestamp": 1770164642,
        "date": "2026-02-04"
      },
      {
        "hash": "3252B308F03FF5F143A3D30455A9D6C553102FCA27F9FB576A228B88D458F93F",
        "recipient": "rH3dfGifdXzghxKXS74WRA3WtdKLKGj5Um",
        "pft": 5500,
        "timestamp": 1770164130,
        "date": "2026-02-04"
      },
      {
        "hash": "FC7C11213A949354AB1490AF0412A0454C016F95379FD66ED1C589AC3644029D",
        "recipient": "rPo8GkCA9YMKzuJGTHbj11kdVfPqSJHxNx",
        "pft": 6000,
        "timestamp": 1770164130,
        "date": "2026-02-04"
      },
      {
        "hash": "C2C98511DF056148154F131F840E4647C91E1C72F39E5515A632B4D03B782094",
        "recipient": "r4r2Kfe7hH72gb1owkkrWa9miHE9n3xJi4",
        "pft": 3500,
        "timestamp": 1770155920,
        "date": "2026-02-03"
      },
      {
        "hash": "B325393A66FC53131E05158BE3D17D464E2059C77502531AF2EAD98F93AE0973",
        "recipient": "rHTgM9rZBZkuqF5H8DQxFWTR7biXmMvPLm",
        "pft": 8625,
        "timestamp": 1770155102,
        "date": "2026-02-03"
      },
      {
        "hash": "D94D19FB3C13D968A46E2542CB7621B3BD5E64A4DB3BC28333774163DD33A2EB",
        "recipient": "rHTgM9rZBZkuqF5H8DQxFWTR7biXmMvPLm",
        "pft": 5500,
        "timestamp": 1770152801,
        "date": "2026-02-03"
      },
      {
        "hash": "C1CC7B2A24E7550B1B8857F175D6EC4692072D74C77A5B34593B2DF3B977CF4F",
        "recipient": "rGGodJFqgreLgXKVGspkZ68dqBH8RBGCJr",
        "pft": 5000,
        "timestamp": 1770149922,
        "date": "2026-02-03"
      },
      {
        "hash": "17B5D3A5873A993D245B80D405FA4326285580217889088FA4AAB01FC96AE7D1",
        "recipient": "rnmLkDT2SBeaFA5z2ogdUCbJ2GMzn2sLLu",
        "pft": 6000,
        "timestamp": 1770147062,
        "date": "2026-02-03"
      },
      {
        "hash": "7B6FA7BB543D724AF2BDFFE3F9BB2D009DC41DD0E3B3762E5124D182EECAA8F5",
        "recipient": "rPo8GkCA9YMKzuJGTHbj11kdVfPqSJHxNx",
        "pft": 250,
        "timestamp": 1770143471,
        "date": "2026-02-03"
      },
      {
        "hash": "693A47B9EFFA5EA0BCE3A32DB65AF038726DDD92AAB229A8919F6B203036A237",
        "recipient": "rPo8GkCA9YMKzuJGTHbj11kdVfPqSJHxNx",
        "pft": 8500,
        "timestamp": 1770140860,
        "date": "2026-02-03"
      },
      {
        "hash": "A65E431DA50728621260D6630841CC2FCE5054F4874DD7ACB764AF3189421F1E",
        "recipient": "rnmLkDT2SBeaFA5z2ogdUCbJ2GMzn2sLLu",
        "pft": 7000,
        "timestamp": 1770129781,
        "date": "2026-02-03"
      },
      {
        "hash": "55DE6F26C76E295E3E48571449B23E1E398BB2D8B03314D718537D034A09AB33",
        "recipient": "rDqf4nowC2PAZgn1UGHDn46mcUMREYJrsr",
        "pft": 9800,
        "timestamp": 1770127073,
        "date": "2026-02-03"
      },
      {
        "hash": "10AE11D4D809B7506215B225BA4F52F5C03F2BDA5564D237C95314B2B04553C7",
        "recipient": "rDqf4nowC2PAZgn1UGHDn46mcUMREYJrsr",
        "pft": 10000,
        "timestamp": 1770122151,
        "date": "2026-02-03"
      },
      {
        "hash": "DD757FDB9FE256EBB1792FA9773F50C162E164A2207FE50E2300BD84B525CBAE",
        "recipient": "rnmLkDT2SBeaFA5z2ogdUCbJ2GMzn2sLLu",
        "pft": 9500,
        "timestamp": 1770112412,
        "date": "2026-02-03"
      },
      {
        "hash": "BCBB9CF268DB96974BA88B34B4B4F0EAF15A7A8164E8FEF83E6AF79B2C54C7BF",
        "recipient": "rpc9FcxtaNVdWonAXv3rABecNLx7kcA3sY",
        "pft": 7000,
        "timestamp": 1770112310,
        "date": "2026-02-03"
      },
      {
        "hash": "FB02CE638B7C5310F3F35BE78B106B04A5B6EBC36E7BF520AAC42E04B6EB3C5A",
        "recipient": "rpc9FcxtaNVdWonAXv3rABecNLx7kcA3sY",
        "pft": 5500,
        "timestamp": 1770100532,
        "date": "2026-02-03"
      },
      {
        "hash": "E31F87B0B56E1AFDFEF7B17441B0B69F4C5BDF5789957D3A71C31805A9ED17F6",
        "recipient": "r4WS8fhYgpvnV5j4qkb7yvbt96Bvx9gMZH",
        "pft": 5500,
        "timestamp": 1770098380,
        "date": "2026-02-03"
      },
      {
        "hash": "F060A78EBFCBBBF536A7CCDC39AAEC92069F4C968455B48F3D74F746A887428A",
        "recipient": "rh7eykJ99XnGTm2iNBzeD5A9MLqnb7kXCp",
        "pft": 8000,
        "timestamp": 1770081473,
        "date": "2026-02-03"
      },
      {
        "hash": "9900A7B9F0F2E3F6F1880B98FBE552E669CA0A05CF25AFFF8B9890FE19ED9A77",
        "recipient": "rh7eykJ99XnGTm2iNBzeD5A9MLqnb7kXCp",
        "pft": 5000,
        "timestamp": 1770081432,
        "date": "2026-02-03"
      },
      {
        "hash": "CC2BAFD9E05E8ADC37DEC914BC16DC771FCC090028F4700988262996446CB597",
        "recipient": "rh7eykJ99XnGTm2iNBzeD5A9MLqnb7kXCp",
        "pft": 7500,
        "timestamp": 1770081383,
        "date": "2026-02-03"
      },
      {
        "hash": "5234D07B571A35F333D974078FACD61E6A282E67CC37456D400D84A91CD34489",
        "recipient": "rh7eykJ99XnGTm2iNBzeD5A9MLqnb7kXCp",
        "pft": 6300,
        "timestamp": 1770081342,
        "date": "2026-02-03"
      },
      {
        "hash": "360797809BB0A4A01644E144ED9D4B6855FA2C3490C630A184EEE2E7C0299F97",
        "recipient": "rpyTMcAKiCxqY7VXenD5ercGGzGWNV9xpg",
        "pft": 1515.625,
        "timestamp": 1770081291,
        "date": "2026-02-03"
      },
      {
        "hash": "26A46AD68AE03D5F37124C7CA5E811DE358916E202B55F9CAEB6D8A89307E136",
        "recipient": "rnmLkDT2SBeaFA5z2ogdUCbJ2GMzn2sLLu",
        "pft": 5000,
        "timestamp": 1770081130,
        "date": "2026-02-03"
      },
      {
        "hash": "8B0FD929C8560DFC623F4DB7CE9CB861014A3D19BB8F2695F98772AEEA6B0F2D",
        "recipient": "rH3dfGifdXzghxKXS74WRA3WtdKLKGj5Um",
        "pft": 9500,
        "timestamp": 1770080521,
        "date": "2026-02-03"
      },
      {
        "hash": "62F8463793AAD4BBFFFADC110AC22AF99D82A4F11D4E446C583B0A177BCA8927",
        "recipient": "rDxG2EXUmQThZJtZcq4cp18obb8gU7oxuR",
        "pft": 8000,
        "timestamp": 1770079880,
        "date": "2026-02-03"
      },
      {
        "hash": "9DC00E1F377A905C3FB4FCD82CE87588DB299752AC310D9770AA99C384ECDF73",
        "recipient": "rDqf4nowC2PAZgn1UGHDn46mcUMREYJrsr",
        "pft": 6250,
        "timestamp": 1770079230,
        "date": "2026-02-03"
      },
      {
        "hash": "DC8BAE144B2CEC05A63A6E75A9FC1B120019E6E0979F1F3BE458CE659F80E9DD",
        "recipient": "r4r2Kfe7hH72gb1owkkrWa9miHE9n3xJi4",
        "pft": 2000,
        "timestamp": 1770078940,
        "date": "2026-02-03"
      },
      {
        "hash": "ECE1CE3044A78915518A85BD189083504E98F782E195B505BE233CABE999F20D",
        "recipient": "rDqf4nowC2PAZgn1UGHDn46mcUMREYJrsr",
        "pft": 8500,
        "timestamp": 1770075722,
        "date": "2026-02-02"
      },
      {
        "hash": "BB094A82501AEE9CDC6795C9D2997C7437D52B3A3847A7715DB8524693A21DF9",
        "recipient": "rH3dfGifdXzghxKXS74WRA3WtdKLKGj5Um",
        "pft": 9500,
        "timestamp": 1770075382,
        "date": "2026-02-02"
      },
      {
        "hash": "526A705A2A97008D119B75B596353AFDEA5B47E6AA8BEB6E217AA4DB06ED34FF",
        "recipient": "rh7eykJ99XnGTm2iNBzeD5A9MLqnb7kXCp",
        "pft": 6500,
        "timestamp": 1770073723,
        "date": "2026-02-02"
      },
      {
        "hash": "38F1A937CCBFD96528475A8940885E06A8B9841CE7F597E80BB150ECAE74299A",
        "recipient": "rDqf4nowC2PAZgn1UGHDn46mcUMREYJrsr",
        "pft": 10000,
        "timestamp": 1770073222,
        "date": "2026-02-02"
      },
      {
        "hash": "630EBC4E7DBACAFBD44FF5868AC860C3B01EAEE70602151525BEBBF90DFE4DC2",
        "recipient": "rDqf4nowC2PAZgn1UGHDn46mcUMREYJrsr",
        "pft": 10000,
        "timestamp": 1770072431,
        "date": "2026-02-02"
      },
      {
        "hash": "6F5E5B69389C56B3C2134D4BC811FE9A32773B46736A50EFFDC37C7F0FAEAAB0",
        "recipient": "rnmLkDT2SBeaFA5z2ogdUCbJ2GMzn2sLLu",
        "pft": 9500,
        "timestamp": 1770071121,
        "date": "2026-02-02"
      },
      {
        "hash": "A263A0F2153F1088D4ED55ED16D3CE253CD6B12D6C073C2B2CBAC6154BDB9D81",
        "recipient": "rDqf4nowC2PAZgn1UGHDn46mcUMREYJrsr",
        "pft": 9600,
        "timestamp": 1770067942,
        "date": "2026-02-02"
      },
      {
        "hash": "F8B6B1001D91DBD2D71B99A1C134D44079FC169E621D5F7BFE26C1327CEE7CB0",
        "recipient": "rDqf4nowC2PAZgn1UGHDn46mcUMREYJrsr",
        "pft": 10000,
        "timestamp": 1770064992,
        "date": "2026-02-02"
      },
      {
        "hash": "79CCEC255F3018E28CCD8D38FC3D1E6F603DF2F2E26B21B7D03DA0155792512F",
        "recipient": "r9oHNN143VkaVeQ5kfQnRyc9gwL8HhSa32",
        "pft": 8750,
        "timestamp": 1770064901,
        "date": "2026-02-02"
      },
      {
        "hash": "28DD24FEC3759C48F6B37D60CBF316DA5748C25CA1B83130A96821140849510D",
        "recipient": "rDqf4nowC2PAZgn1UGHDn46mcUMREYJrsr",
        "pft": 9500,
        "timestamp": 1770063982,
        "date": "2026-02-02"
      },
      {
        "hash": "7849AF39D37FD60899A83EFBAA9BA7FC86E2377FD9EBDE0E99BA4686BD2BE462",
        "recipient": "rDqf4nowC2PAZgn1UGHDn46mcUMREYJrsr",
        "pft": 9500,
        "timestamp": 1770062551,
        "date": "2026-02-02"
      },
      {
        "hash": "66DFB04296D000CD9C1FE017CA99B7A2659482CA0BE7A7CDDB5CADBB462CEC39",
        "recipient": "rDqf4nowC2PAZgn1UGHDn46mcUMREYJrsr",
        "pft": 10000,
        "timestamp": 1770061402,
        "date": "2026-02-02"
      },
      {
        "hash": "5CB6A6DDFEFCF7553F4422A0DACEDF31D85383E8EF9117D6BC179BA661E84F28",
        "recipient": "rDqf4nowC2PAZgn1UGHDn46mcUMREYJrsr",
        "pft": 7250,
        "timestamp": 1770060081,
        "date": "2026-02-02"
      },
      {
        "hash": "098832EA43022DCC014AC2DBF84AE18D744CDAB90AB7EC310AF5923550E4364D",
        "recipient": "rDqf4nowC2PAZgn1UGHDn46mcUMREYJrsr",
        "pft": 10000,
        "timestamp": 1770058521,
        "date": "2026-02-02"
      },
      {
        "hash": "E603566AEBC3E193A5BADE69DA301D7708943505BA24230148A9475573854D1B",
        "recipient": "rnmLkDT2SBeaFA5z2ogdUCbJ2GMzn2sLLu",
        "pft": 9500,
        "timestamp": 1770056372,
        "date": "2026-02-02"
      },
      {
        "hash": "226EC909A5FB7CBE6856028176C428A46103FAA78BB89CA8716438BE7AFFE554",
        "recipient": "rDqf4nowC2PAZgn1UGHDn46mcUMREYJrsr",
        "pft": 10000,
        "timestamp": 1770056091,
        "date": "2026-02-02"
      },
      {
        "hash": "4ED4E9AB8E1658CC85C8051E93D9DEFED51C0E38F7A7D81F57B56B819E0F6FD7",
        "recipient": "rDqf4nowC2PAZgn1UGHDn46mcUMREYJrsr",
        "pft": 10000,
        "timestamp": 1770053371,
        "date": "2026-02-02"
      },
      {
        "hash": "39F8390D2AB18CDABF28A87C5C79AEBE7C0D783EF7F0E2B9F5E9869BA95143DA",
        "recipient": "rDqf4nowC2PAZgn1UGHDn46mcUMREYJrsr",
        "pft": 9750,
        "timestamp": 1770051541,
        "date": "2026-02-02"
      }
    ]
  },
  "submissions": {
    "total_submissions": 744,
    "unique_submitters": 39,
    "top_submitters": [
      {
        "address": "rDqf4nowC2PAZgn1UGHDn46mcUMREYJrsr",
        "submissions": 151
      },
      {
        "address": "rh7eykJ99XnGTm2iNBzeD5A9MLqnb7kXCp",
        "submissions": 102
      },
      {
        "address": "rPo8GkCA9YMKzuJGTHbj11kdVfPqSJHxNx",
        "submissions": 88
      },
      {
        "address": "rnmLkDT2SBeaFA5z2ogdUCbJ2GMzn2sLLu",
        "submissions": 86
      },
      {
        "address": "r4LPPHygwNnM5d9xtFDnR9hsBqyQQKauGh",
        "submissions": 34
      },
      {
        "address": "rpyTMcAKiCxqY7VXenD5ercGGzGWNV9xpg",
        "submissions": 27
      },
      {
        "address": "rH3dfGifdXzghxKXS74WRA3WtdKLKGj5Um",
        "submissions": 22
      },
      {
        "address": "rHTgM9rZBZkuqF5H8DQxFWTR7biXmMvPLm",
        "submissions": 21
      },
      {
        "address": "rpc9FcxtaNVdWonAXv3rABecNLx7kcA3sY",
        "submissions": 15
      },
      {
        "address": "rDxG2EXUmQThZJtZcq4cp18obb8gU7oxuR",
        "submissions": 15
      },
      {
        "address": "rfo5PXejjp6xA4H8cNhodhkfz9tHLMCVNx",
        "submissions": 15
      },
      {
        "address": "rLdQP33f66jmUo77AG9jCqgNcRC4URxKhp",
        "submissions": 15
      },
      {
        "address": "rQhV9rE7cs5zgFZohjVjjbwqcMkwpLb9rE",
        "submissions": 14
      },
      {
        "address": "r9oHNN143VkaVeQ5kfQnRyc9gwL8HhSa32",
        "submissions": 13
      },
      {
        "address": "rKZ9SVg1z764ABrLQ3Q1Dh5PPR7gM1z4Df",
        "submissions": 10
      },
      {
        "address": "rsAGhYorBXGmbDGXR23iwnENSwSuoMfkQZ",
        "submissions": 10
      },
      {
        "address": "rMghCB7NxDV3PfgFTLkzF1YT2KovKEFRWN",
        "submissions": 10
      },
      {
        "address": "rafVsZMGoPbMfaJi3Ty8fTWVA2cfq8an5C",
        "submissions": 10
      },
      {
        "address": "rGGodJFqgreLgXKVGspkZ68dqBH8RBGCJr",
        "submissions": 9
      },
      {
        "address": "r4r2Kfe7hH72gb1owkkrWa9miHE9n3xJi4",
        "submissions": 8
      },
      {
        "address": "rDAokUXBoYRRqwB3z97t7EsS4ASdXopfo1",
        "submissions": 8
      },
      {
        "address": "r4WS8fhYgpvnV5j4qkb7yvbt96Bvx9gMZH",
        "submissions": 7
      },
      {
        "address": "r4DQiSf6DaKk5ZDe46BmMFKC4ooZCBtpkn",
        "submissions": 7
      },
      {
        "address": "rPfbHPUixxMkebvrCKwv3KeJLNMktHDT67",
        "submissions": 6
      },
      {
        "address": "r1uESHeCB7ZooX1H6xrok754dama1gTWs",
        "submissions": 6
      }
    ],
    "daily_submissions": [
      {
        "date": "2026-01-18",
        "submissions": 12
      },
      {
        "date": "2026-01-19",
        "submissions": 17
      },
      {
        "date": "2026-01-20",
        "submissions": 7
      },
      {
        "date": "2026-01-21",
        "submissions": 30
      },
      {
        "date": "2026-01-22",
        "submissions": 21
      },
      {
        "date": "2026-01-23",
        "submissions": 16
      },
      {
        "date": "2026-01-24",
        "submissions": 22
      },
      {
        "date": "2026-01-25",
        "submissions": 10
      },
      {
        "date": "2026-01-26",
        "submissions": 2
      },
      {
        "date": "2026-01-27",
        "submissions": 5
      },
      {
        "date": "2026-01-28",
        "submissions": 11
      },
      {
        "date": "2026-01-29",
        "submissions": 21
      },
      {
        "date": "2026-01-30",
        "submissions": 139
      },
      {
        "date": "2026-01-31",
        "submissions": 45
      },
      {
        "date": "2026-02-01",
        "submissions": 88
      },
      {
        "date": "2026-02-02",
        "submissions": 158
      },
      {
        "date": "2026-02-03",
        "submissions": 96
      },
      {
        "date": "2026-02-04",
        "submissions": 44
      }
    ],
    "recent_submissions": [
      {
        "hash": "",
        "sender": "rH3dfGifdXzghxKXS74WRA3WtdKLKGj5Um",
        "timestamp": 1770180240,
        "date": "2026-02-04"
      },
      {
        "hash": "",
        "sender": "rH3dfGifdXzghxKXS74WRA3WtdKLKGj5Um",
        "timestamp": 1770180181,
        "date": "2026-02-04"
      },
      {
        "hash": "",
        "sender": "rH3dfGifdXzghxKXS74WRA3WtdKLKGj5Um",
        "timestamp": 1770176612,
        "date": "2026-02-04"
      },
      {
        "hash": "",
        "sender": "rH3dfGifdXzghxKXS74WRA3WtdKLKGj5Um",
        "timestamp": 1770176560,
        "date": "2026-02-04"
      },
      {
        "hash": "",
        "sender": "rh7eykJ99XnGTm2iNBzeD5A9MLqnb7kXCp",
        "timestamp": 1770176502,
        "date": "2026-02-04"
      },
      {
        "hash": "",
        "sender": "rh7eykJ99XnGTm2iNBzeD5A9MLqnb7kXCp",
        "timestamp": 1770176471,
        "date": "2026-02-04"
      },
      {
        "hash": "",
        "sender": "rh7eykJ99XnGTm2iNBzeD5A9MLqnb7kXCp",
        "timestamp": 1770176400,
        "date": "2026-02-04"
      },
      {
        "hash": "",
        "sender": "rh7eykJ99XnGTm2iNBzeD5A9MLqnb7kXCp",
        "timestamp": 1770176361,
        "date": "2026-02-04"
      },
      {
        "hash": "",
        "sender": "rpc9FcxtaNVdWonAXv3rABecNLx7kcA3sY",
        "timestamp": 1770176200,
        "date": "2026-02-04"
      },
      {
        "hash": "",
        "sender": "rpc9FcxtaNVdWonAXv3rABecNLx7kcA3sY",
        "timestamp": 1770175491,
        "date": "2026-02-04"
      },
      {
        "hash": "",
        "sender": "rh7eykJ99XnGTm2iNBzeD5A9MLqnb7kXCp",
        "timestamp": 1770175261,
        "date": "2026-02-04"
      },
      {
        "hash": "",
        "sender": "rh7eykJ99XnGTm2iNBzeD5A9MLqnb7kXCp",
        "timestamp": 1770175260,
        "date": "2026-02-04"
      },
      {
        "hash": "",
        "sender": "rh7eykJ99XnGTm2iNBzeD5A9MLqnb7kXCp",
        "timestamp": 1770175253,
        "date": "2026-02-04"
      },
      {
        "hash": "",
        "sender": "rh7eykJ99XnGTm2iNBzeD5A9MLqnb7kXCp",
        "timestamp": 1770175112,
        "date": "2026-02-04"
      },
      {
        "hash": "",
        "sender": "rh7eykJ99XnGTm2iNBzeD5A9MLqnb7kXCp",
        "timestamp": 1770175112,
        "date": "2026-02-04"
      },
      {
        "hash": "",
        "sender": "rh7eykJ99XnGTm2iNBzeD5A9MLqnb7kXCp",
        "timestamp": 1770175111,
        "date": "2026-02-04"
      },
      {
        "hash": "",
        "sender": "rpyTMcAKiCxqY7VXenD5ercGGzGWNV9xpg",
        "timestamp": 1770174492,
        "date": "2026-02-04"
      },
      {
        "hash": "",
        "sender": "rHTgM9rZBZkuqF5H8DQxFWTR7biXmMvPLm",
        "timestamp": 1770174222,
        "date": "2026-02-04"
      },
      {
        "hash": "",
        "sender": "rpyTMcAKiCxqY7VXenD5ercGGzGWNV9xpg",
        "timestamp": 1770174203,
        "date": "2026-02-04"
      },
      {
        "hash": "",
        "sender": "rHTgM9rZBZkuqF5H8DQxFWTR7biXmMvPLm",
        "timestamp": 1770173871,
        "date": "2026-02-04"
      },
      {
        "hash": "",
        "sender": "rnmLkDT2SBeaFA5z2ogdUCbJ2GMzn2sLLu",
        "timestamp": 1770173853,
        "date": "2026-02-04"
      },
      {
        "hash": "",
        "sender": "rnmLkDT2SBeaFA5z2ogdUCbJ2GMzn2sLLu",
        "timestamp": 1770173771,
        "date": "2026-02-04"
      },
      {
        "hash": "",
        "sender": "rnmLkDT2SBeaFA5z2ogdUCbJ2GMzn2sLLu",
        "timestamp": 1770173010,
        "date": "2026-02-04"
      },
      {
        "hash": "",
        "sender": "rHTgM9rZBZkuqF5H8DQxFWTR7biXmMvPLm",
        "timestamp": 1770172230,
        "date": "2026-02-04"
      },
      {
        "hash": "",
        "sender": "rHTgM9rZBZkuqF5H8DQxFWTR7biXmMvPLm",
        "timestamp": 1770172050,
        "date": "2026-02-04"
      },
      {
        "hash": "",
        "sender": "rpyTMcAKiCxqY7VXenD5ercGGzGWNV9xpg",
        "timestamp": 1770170420,
        "date": "2026-02-04"
      },
      {
        "hash": "",
        "sender": "rpyTMcAKiCxqY7VXenD5ercGGzGWNV9xpg",
        "timestamp": 1770170331,
        "date": "2026-02-04"
      },
      {
        "hash": "",
        "sender": "rpyTMcAKiCxqY7VXenD5ercGGzGWNV9xpg",
        "timestamp": 1770168680,
        "date": "2026-02-04"
      },
      {
        "hash": "",
        "sender": "rpyTMcAKiCxqY7VXenD5ercGGzGWNV9xpg",
        "timestamp": 1770168550,
        "date": "2026-02-04"
      },
      {
        "hash": "",
        "sender": "rpyTMcAKiCxqY7VXenD5ercGGzGWNV9xpg",
        "timestamp": 1770168201,
        "date": "2026-02-04"
      },
      {
        "hash": "",
        "sender": "rpyTMcAKiCxqY7VXenD5ercGGzGWNV9xpg",
        "timestamp": 1770168090,
        "date": "2026-02-04"
      },
      {
        "hash": "",
        "sender": "rpyTMcAKiCxqY7VXenD5ercGGzGWNV9xpg",
        "timestamp": 1770167292,
        "date": "2026-02-04"
      },
      {
        "hash": "",
        "sender": "rpyTMcAKiCxqY7VXenD5ercGGzGWNV9xpg",
        "timestamp": 1770167161,
        "date": "2026-02-04"
      },
      {
        "hash": "",
        "sender": "rDqf4nowC2PAZgn1UGHDn46mcUMREYJrsr",
        "timestamp": 1770166470,
        "date": "2026-02-04"
      },
      {
        "hash": "",
        "sender": "rDqf4nowC2PAZgn1UGHDn46mcUMREYJrsr",
        "timestamp": 1770166163,
        "date": "2026-02-04"
      },
      {
        "hash": "",
        "sender": "rnmLkDT2SBeaFA5z2ogdUCbJ2GMzn2sLLu",
        "timestamp": 1770165961,
        "date": "2026-02-04"
      },
      {
        "hash": "",
        "sender": "rnmLkDT2SBeaFA5z2ogdUCbJ2GMzn2sLLu",
        "timestamp": 1770165871,
        "date": "2026-02-04"
      },
      {
        "hash": "",
        "sender": "rnmLkDT2SBeaFA5z2ogdUCbJ2GMzn2sLLu",
        "timestamp": 1770164751,
        "date": "2026-02-04"
      },
      {
        "hash": "",
        "sender": "rDqf4nowC2PAZgn1UGHDn46mcUMREYJrsr",
        "timestamp": 1770164610,
        "date": "2026-02-04"
      },
      {
        "hash": "",
        "sender": "rDqf4nowC2PAZgn1UGHDn46mcUMREYJrsr",
        "timestamp": 1770164312,
        "date": "2026-02-04"
      },
      {
        "hash": "",
        "sender": "rPo8GkCA9YMKzuJGTHbj11kdVfPqSJHxNx",
        "timestamp": 1770164100,
        "date": "2026-02-04"
      },
      {
        "hash": "",
        "sender": "rH3dfGifdXzghxKXS74WRA3WtdKLKGj5Um",
        "timestamp": 1770164070,
        "date": "2026-02-04"
      },
      {
        "hash": "",
        "sender": "rH3dfGifdXzghxKXS74WRA3WtdKLKGj5Um",
        "timestamp": 1770163871,
        "date": "2026-02-04"
      },
      {
        "hash": "",
        "sender": "rPo8GkCA9YMKzuJGTHbj11kdVfPqSJHxNx",
        "timestamp": 1770163821,
        "date": "2026-02-04"
      },
      {
        "hash": "",
        "sender": "rDxG2EXUmQThZJtZcq4cp18obb8gU7oxuR",
        "timestamp": 1770159922,
        "date": "2026-02-03"
      },
      {
        "hash": "",
        "sender": "rDxG2EXUmQThZJtZcq4cp18obb8gU7oxuR",
        "timestamp": 1770158070,
        "date": "2026-02-03"
      },
      {
        "hash": "",
        "sender": "rDxG2EXUmQThZJtZcq4cp18obb8gU7oxuR",
        "timestamp": 1770157412,
        "date": "2026-02-03"
      },
      {
        "hash": "",
        "sender": "r4r2Kfe7hH72gb1owkkrWa9miHE9n3xJi4",
        "timestamp": 1770157362,
        "date": "2026-02-03"
      },
      {
        "hash": "",
        "sender": "r4r2Kfe7hH72gb1owkkrWa9miHE9n3xJi4",
        "timestamp": 1770156062,
        "date": "2026-02-03"
      },
      {
        "hash": "",
        "sender": "r4r2Kfe7hH72gb1owkkrWa9miHE9n3xJi4",
        "timestamp": 1770155881,
        "date": "2026-02-03"
      }
    ]
  },
  "task_lifecycle": {
    "total_tasks_inferred": 449,
    "tasks_completed": 271,
    "tasks_pending": 17,
    "tasks_expired": 161,
    "completion_rate": 60.35634743875279,
    "avg_time_to_reward_hours": 0.14,
    "daily_lifecycle": [
      {
        "date": "2026-01-18",
        "submitted": 8,
        "completed": 0,
        "expired": 0
      },
      {
        "date": "2026-01-19",
        "submitted": 15,
        "completed": 0,
        "expired": 8
      },
      {
        "date": "2026-01-20",
        "submitted": 6,
        "completed": 0,
        "expired": 15
      },
      {
        "date": "2026-01-21",
        "submitted": 19,
        "completed": 9,
        "expired": 6
      },
      {
        "date": "2026-01-22",
        "submitted": 12,
        "completed": 9,
        "expired": 10
      },
      {
        "date": "2026-01-23",
        "submitted": 9,
        "completed": 6,
        "expired": 3
      },
      {
        "date": "2026-01-24",
        "submitted": 15,
        "completed": 7,
        "expired": 3
      },
      {
        "date": "2026-01-25",
        "submitted": 6,
        "completed": 3,
        "expired": 8
      },
      {
        "date": "2026-01-26",
        "submitted": 1,
        "completed": 1,
        "expired": 3
      },
      {
        "date": "2026-01-27",
        "submitted": 3,
        "completed": 2,
        "expired": 0
      },
      {
        "date": "2026-01-28",
        "submitted": 6,
        "completed": 4,
        "expired": 1
      },
      {
        "date": "2026-01-29",
        "submitted": 16,
        "completed": 4,
        "expired": 2
      },
      {
        "date": "2026-01-30",
        "submitted": 80,
        "completed": 46,
        "expired": 12
      },
      {
        "date": "2026-01-31",
        "submitted": 26,
        "completed": 16,
        "expired": 34
      },
      {
        "date": "2026-02-01",
        "submitted": 52,
        "completed": 32,
        "expired": 10
      },
      {
        "date": "2026-02-02",
        "submitted": 94,
        "completed": 74,
        "expired": 19
      },
      {
        "date": "2026-02-03",
        "submitted": 57,
        "completed": 38,
        "expired": 21
      },
      {
        "date": "2026-02-04",
        "submitted": 24,
        "completed": 20,
        "expired": 6
      }
    ]
  }
}